Hello123/__init__.py
Hello123/main.py
Hello123-0.0.1.dist-info/LICENSE
Hello123-0.0.1.dist-info/METADATA
Hello123-0.0.1.dist-info/WHEEL
Hello123-0.0.1.dist-info/top_level.txt
Hello123-0.0.1.dist-info/RECORD
